[
{"state":"Assam State Zoo","ll":[91.735551,26.147129]},
{"state":"Kankaria Zoo","ll":[72.566004,23.039568]},
{"state":"Aizawl Zoo","ll":[92.717639,23.2]},
{"state":"Nandankanan Zoo","ll":[85.82454,20.296059]},
{"state":"Vandalur Zoo/ Snake and Crocodile Park","ll":[80.250825,13.052414]},
{"state":"Padmaja Naidu Himalayan Zoo","ll":[88.262675,27.036007]},
{"state":"National Zoological Park","ll":[77.22496,28.635308]},
{"state":"Nehru Zoological Park","ll":[78.486671,17.385044]},
{"state":"Indore Zoo","ll":[75.857726,22.719569]},
{"state":"Jaipur Zoo","ll":[75.787288,26.912416]},
{"state":"Thim Park","ll":[86.202875,22.804566]},
{"state":"Jhargram Zoo","ll":[86.99589,22.2]},
{"state":"Sakkarbaug Zoo","ll":[70.457877,21.522184]},
{"state":"Marble Palace zoo","ll":[89.563895,22.572646]},
{"state":"Lucknow Zoo","ll":[80.946683,26.846511]},
{"state":"Jijamata Udyaan","ll":[72.877656,19.075984]},
{"state":"Mysore Zoo","ll":[76.639381,12.29581]},
{"state":"Pt. G.B. Pant High Altitude Zoo","ll":[79.463566,29.380304]},
{"state":"Sanjay Gandhi Jaivik Udyan","ll":[85.141667,25.61046]},
{"state":"Rajiv Gandhi Zoological Park","ll":[73.856744,18.52043]},
{"state":"Birsa Deer Park and Ranchi Zoo","ll":[85.309562,23.3441]},
{"state":"Tilyar Zoo","ll":[76.59124,28.0]},
{"state":"Sarthana Zoo","ll":[72.819444,21.195]},
{"state":"Thrissur Zoo","ll":[76.214435,10.527642]},
{"state":"Sri Venkateswara Zoological Park","ll":[79.419179,13.628756]},
{"state":"Sipahijola Wildlife Sanctuary","ll":[91.988153,23.940848]},
{"state":"Thiruvananthapuram Zoo","ll":[76.948623,8.487495]},
{"state":"Gulab Bagh and Zoo","ll":[73.691544,24.57127]},
{"state":"Sayaji Baug Zoo","ll":[73.181098,22.307309]},
{"state":"Indira Gandhi Zoological Park","ll":[83.218482,17.686816]},
{"state":"ChattBir Zoo","ll":[76.817336,30.64255]}
]
